{
  "institution": null,
  "coverPhoto": {
    "id": 112876,
    "imageId": "a20ce20a-b2eb-4b1f-91a0-a3e083a51b3b",
    "imagePath": "e016d066-ccbf-4d7c-b5af-acaf1088c988121e485e-be26-4b2c-a45e-a0f90e2745ef.png",
    "url": "https://se-images-blob.campuslabs.com/communities/3777/coverphotos/a20ce20a-b2eb-4b1f-91a0-a3e083a51b3b.jpg",
    "thumbnailUrl": "https://se-images-blob.campuslabs.com/communities/3777/coverphotos/a20ce20a-b2eb-4b1f-91a0-a3e083a51b3b-thumbnail.jpg",
    "caption": "Uploaded cover photo has no appropriate alternative text",
    "dateCreated": "2018-11-21T12:25:56-05:00",
    "institutionId": 3777
  },
  "user": null,
  "preFetchedData": {
    "event": null,
    "loadAdditionalEventDetails": false,
    "organization": {
      "id": 250730,
      "communityId": 1018,
      "institutionId": 3777,
      "name": "Iranian Students Association of Portland",
      "shortName": "ISAP",
      "nameSortKey": "I",
      "websiteKey": "iranian-students-association-of-portland",
      "email": null,
      "description": "<p>Iranian Student Association of Portland (ISAP) is a non-profit and non-religious organization. Our mission is to provide support for new and continuing Iranian students at PSU, promote academic success, carry on Iranian traditions within the Portland community, and holding cultural events. We intend to be a point of contact to students and Iranian people new to the area. The Iranian student association of Portland intends to unify the Iranian community, regardless of background, in pursuit of a deeper sense of cultural, historical and communal identity. In addition, we celebrate Iranian cultural and historical holidays (i.e. Nowruz, Sepandarmazgan, Sizdeh-be-dar, Mehregan, Sadeh, Yalda), organize group outings, sporting events, and day hikes, and have viewing parties for various Iranian movies. The officers, members, as well as the support of the Iranian community, strive to promote a better understanding of the social, traditional, and historical aspect of the Iranian culture. ISAP is proud to present our culture to the Iranian students as well as students of different ethnic backgrounds.</p>",
      "summary": "Iranian Student Association of Portland (ISAP) is a non-profit and non-religious organization. Our mission is to provide support for new and continuing Iranian students at PSU, promote academic success, carry on Iranian traditions within the Portland c...",
      "status": "Active",
      "comment": null,
      "showJoin": true,
      "statusChangeDateTime": null,
      "startDate": "2019-05-28T00:00:00-04:00",
      "endDate": null,
      "parentId": 222232,
      "wallId": 20359036,
      "discussionId": 20359036,
      "groupTypeId": null,
      "organizationTypeId": 20678,
      "cssConfigurationId": null,
      "deleted": false,
      "enableGoogleCalendar": false,
      "modifiedOn": "2019-10-09T19:30:51-04:00",
      "socialMedia": {
        "externalWebsite": "",
        "flickrUrl": "",
        "googleCalendarUrl": "",
        "googlePlusUrl": "",
        "instagramUrl": "https://www.instagram.com/isap.pdx/",
        "linkedInUrl": "",
        "pinterestUrl": "",
        "tumblrUrl": "",
        "vimeoUrl": "",
        "youtubeUrl": "",
        "facebookUrl": "https://www.facebook.com/isap.pdx",
        "twitterUrl": "",
        "twitterUserName": null
      },
      "profilePicture": "e869becf-9c17-4f56-ab3f-483a76c5642b1c1c5633-dc5c-4c53-9f40-982ab0c36aa0.jpg",
      "organizationType": {
        "id": 20678,
        "name": "Recognized Student Organization (SALP)",
        "autoApproveRequests": false,
        "showMembersToPublic": false,
        "showOfficersToPublic": true,
        "eventsEnabled": true,
        "serviceHoursEnabled": false,
        "financeEnabled": true,
        "financeRequestsEnabled": false,
        "fundingRequestsEnabled": true,
        "purchaseRequestsEnabled": true,
        "budgetingEnabled": true,
        "budgetingRequestsEnabled": true,
        "reRegistrationAvailabilty": null,
        "electionsEnabled": true,
        "formsEnabled": true,
        "galleryEnabled": true,
        "outcomesEnabled": true,
        "rosterEnabled": true,
        "shownInPublicDirectory": true,
        "documentsEnabled": true,
        "isSystemType": false,
        "adminOnly": false
      },
      "primaryContact": {
        "id": "8acb74c7-a7df-4fc3-b95b-023a31967254",
        "firstName": "Bahar",
        "preferredFirstName": null,
        "lastName": "Behboodi",
        "primaryEmailAddress": "behboodi@pdx.edu",
        "profileImageFilePath": null,
        "institutionId": 3777,
        "privacy": "Unselected"
      },
      "isBranch": false,
      "contactInfo": [
        {
          "id": 315845,
          "addressType": 0,
          "city": null,
          "country": null,
          "deleted": false,
          "extension": null,
          "faxNumber": null,
          "organizationId": 250730,
          "phoneNumber": null,
          "state": null,
          "street1": null,
          "street2": null,
          "zip": null
        }
      ],
      "legacyKey": 21891,
      "parentLegacyKey": null,
      "legacyPrimaryContactKey": null,
      "showFacebookWall": false,
      "showTwitterFeed": false,
      "submissions": [],
      "visibility": "Public",
      "isShownInPublicDirectory": true,
      "isAdminOnly": false,
      "categories": []
    },
    "article": null
  },
  "imageServerBaseUrl": "https://se-images.campuslabs.com/clink/images/",
  "baseUrl": "https://pdx.campuslabs.com",
  "serverSideContextRoot": "/engage",
  "serviceOpportunitiesEnabled": true,
  "xsrfToken": "CfDJ8Az9GcAD4TpIm2NmyW6ywWGknLfBNe82xSIL1LZRgdmH6g9ZWruLGMNxkYw-9Yrim1ILr3VSZg_XCKILviPhR_s3665niWOp0KzTkPZYS0VN6ZEgFjbBZgOJNDk8zj9_NNIHgH8UhnkD6GYS3-TGML8",
  "reCaptchaPublicKey": "6LdlpB0TAAAAAJ25ETYC1pRiwGiT7clzxta-HGH0",
  "returnUrl": "",
  "launchDarkly": null
}